insituTools/__init__.py
insituTools/_version.py
insituTools/cli.py
insituTools/algorithm/__init__.py
insituTools/algorithm/extract.py
insituTools/algorithm/globalGMM.py
insituTools/algorithm/localGMM.py
insituTools/algorithm/register.py
insituTools/algorithm/score.py
seu_insitu_tools-0.0.4b0.post3.dist-info/LICENSE
seu_insitu_tools-0.0.4b0.post3.dist-info/METADATA
seu_insitu_tools-0.0.4b0.post3.dist-info/WHEEL
seu_insitu_tools-0.0.4b0.post3.dist-info/entry_points.txt
seu_insitu_tools-0.0.4b0.post3.dist-info/top_level.txt
seu_insitu_tools-0.0.4b0.post3.dist-info/RECORD
