Metadata-Version: 2.1
Name: seu-insitu-tools
Version: 0.0.4b0.post3
Summary: Find and compare In Situ expression in Drosophila embryos
Home-page: https://github.com/zzhmark/insitu-tools
Author: Zuohan Zhao
Author-email: zzhmark@126.com
License: MIT
Platform: UNKNOWN
Classifier: Programming Language :: Python :: 3
Classifier: License :: OSI Approved :: MIT License
Classifier: Operating System :: OS Independent
Requires-Python: >=3.8
Requires-Dist: fire (==0.3.1)
Requires-Dist: numpy (==1.19.1)
Requires-Dist: opencv-python (==4.4.0.44)
Requires-Dist: pandas (==1.1.3)
Requires-Dist: scikit-image (==0.16.2)
Requires-Dist: scikit-learn (==0.23.2)
Requires-Dist: scipy (==1.5.0)
